ipinfopy/__init__.py
ipinfopy/__version__.py
ipinfopy/ipinfo.py
ipinfopy-1.0.0.dist-info/METADATA
ipinfopy-1.0.0.dist-info/WHEEL
ipinfopy-1.0.0.dist-info/top_level.txt
ipinfopy-1.0.0.dist-info/RECORD
