Metadata-Version: 2.1
Name: ipinfopy
Version: 1.0.0
Summary: Python Module for grabbing IPv4 & IPv6 info using ipinfo.io public API
Home-page: https://github.com/cameronpoe/ipinfopy
Author: Cameron Poe
Author-email: cameron@zay.li
License: MIT
Platform: UNKNOWN
Classifier: License :: OSI Approved :: MIT License
Classifier: Programming Language :: Python
Classifier: Programming Language :: Python :: 3
Classifier: Programming Language :: Python :: 3.6
Classifier: Programming Language :: Python :: Implementation :: CPython
Classifier: Programming Language :: Python :: Implementation :: PyPy
Requires-Python: >=3.6.0
